fastapi_grpc_bridge/__init__.py
fastapi_grpc_bridge/cert_utils.py
fastapi_grpc_bridge/config.py
fastapi_grpc_bridge/decorators.py
fastapi_grpc_bridge/generator.py
fastapi_grpc_bridge/grpc_server.py
fastapi_grpc_bridge/utils.py
fastapi_grpc_bridge-0.1.2.dist-info/METADATA
fastapi_grpc_bridge-0.1.2.dist-info/WHEEL
fastapi_grpc_bridge-0.1.2.dist-info/top_level.txt
fastapi_grpc_bridge-0.1.2.dist-info/RECORD
