Metadata-Version: 2.4
Name: fastapi-grpc-bridge
Version: 0.1.2
Summary: Adds gRPC support to FastAPI apps using decorators and Pydantic auto-generation
Home-page: https://github.com/abhishek17569/fastapi-grpc-bridge
Author: Abhishek Mishra
Author-email: Abhishek Mishra <abhishek17569@gmail.com>
License: MIT
Project-URL: Homepage, https://github.com/abhishek17569/fastapi-grpc-bridge
Classifier: Programming Language :: Python :: 3
Classifier: License :: OSI Approved :: MIT License
Requires-Python: >=3.7
Requires-Dist: fastapi
Requires-Dist: grpcio
Requires-Dist: grpcio-tools
Requires-Dist: pydantic
Requires-Dist: protobuf
Requires-Dist: uvicorn
